usbmonitor/__init__.py
usbmonitor/attributes.py
usbmonitor/usbmonitor.py
usbmonitor/__platform_specific_detectors/__init__.py
usbmonitor/__platform_specific_detectors/_constants.py
usbmonitor/__platform_specific_detectors/_darwin_usb_detector.py
usbmonitor/__platform_specific_detectors/_linux_usb_detector.py
usbmonitor/__platform_specific_detectors/_usb_detector_base.py
usbmonitor/__platform_specific_detectors/_windows_usb_detector.py
usb_monitor-1.23.dist-info/LICENSE
usb_monitor-1.23.dist-info/METADATA
usb_monitor-1.23.dist-info/WHEEL
usb_monitor-1.23.dist-info/top_level.txt
usb_monitor-1.23.dist-info/RECORD
